{
	"Overall":
	{
		"ImageEyesGazeDirection": [ -0.99693837781255146, -0.078191245318631489 ],
		"ImageHeadDirection": [ 0.67828010273306583, 0.73480344462748792 ]
	},
	"Landmarks":
	{
		"Neck": [ 320, 315 ],
		"L_Upperarm": [ 456, 418 ],
		"R_Upperarm": [ 184, 418 ],
		"R_LipLower": [ 321, 321 ],
		"L_LipLowerOuter": [ 356, 317 ],
		"R_LipLowerOuter": [ 311, 319 ],
		"L_LipLower": [ 348, 320 ],
		"LipLower": [ 336, 324 ],
		"L_EyelidLower1": [ 372, 229 ],
		"L_EyelidLower": [ 363, 228 ],
		"L_EyelidLower2": [ 380, 227 ],
		"L_LipUpper": [ 353, 306 ],
		"LipUpper": [ 336, 306 ],
		"L_LipCorner": [ 363, 306 ],
		"R_LipUpperOuter": [ 309, 306 ],
		"R_LipUpper": [ 319, 306 ],
		"L_LipUpperOuter": [ 360, 306 ],
		"R_LipCorner": [ 300, 309 ],
		"L_EyeCornerOuter": [ 381, 222 ],
		"L_EyeCornerOuter2": [ 381, 224 ],
		"L_EyeCornerOuter1": [ 382, 220 ],
		"L_EyelashesCorner": [ 382, 220 ],
		"Nose": [ 336, 243 ],
		"R_Nostril": [ 311, 278 ],
		"NoseTip": [ 338, 267 ],
		"NoseLower": [ 337, 281 ],
		"L_Nostril": [ 358, 277 ],
		"C_NoseBridge": [ 337, 206 ],
		"R_Ear": [ 255, 243 ],
		"R_Ear1": [ 255, 243 ],
		"R_Ear3": [ 237, 240 ],
		"R_Ear2": [ 235, 218 ],
		"R_Ear4": [ 249, 264 ],
		"L_EyeCornerInner": [ 353, 224 ],
		"L_EyeCornerInner1": [ 355, 221 ],
		"L_EyeCornerInner2": [ 357, 225 ],
		"R_Eye": [ 295, 220 ],
		"R_Pupil": [ 286, 220 ],
		"R_EyeCornerOuter": [ 279, 221 ],
		"R_EyeCornerOuter1": [ 279, 220 ],
		"R_EyelashesCorner": [ 279, 220 ],
		"R_EyeCornerOuter2": [ 279, 223 ],
		"L_Eye": [ 367, 220 ],
		"L_Pupil": [ 364, 220 ],
		"R_EyeCornerInner": [ 310, 224 ],
		"R_EyeCornerInner2": [ 307, 226 ],
		"R_EyeCornerInner1": [ 308, 221 ],
		"L_Ear1": [ 383, 241 ],
		"L_Ear3": [ 395, 240 ],
		"L_Ear2": [ 397, 217 ],
		"L_Ear4": [ 390, 262 ],
		"L_EyelidUpper1": [ 372, 213 ],
		"L_EyelidUpper2": [ 381, 216 ],
		"L_EyelidUpper": [ 362, 214 ],
		"R_EyelidLower1": [ 291, 229 ],
		"R_EyelidLower2": [ 282, 228 ],
		"R_EyelidLower": [ 300, 228 ],
		"R_EyelidUpper": [ 302, 215 ],
		"R_EyelidUpper1": [ 292, 212 ],
		"R_EyelidUpper2": [ 281, 214 ],
		"C_NoseUpper": [ 336, 225 ]
	}
}