{
	"Overall":
	{
		"ImageEyesGazeDirection": [ -0.85998436028655967, 0.51032038962059589 ],
		"ImageHeadDirection": [ -0.93334560620305951, 0.35897907930886908 ]
	},
	"Landmarks":
	{
		"Neck": [ 320, 315 ],
		"L_Upperarm": [ 456, 418 ],
		"R_Upperarm": [ 184, 418 ],
		"R_LipLower": [ 235, 325 ],
		"L_LipLowerOuter": [ 258, 331 ],
		"R_LipLowerOuter": [ 236, 319 ],
		"L_LipLower": [ 247, 331 ],
		"LipLower": [ 241, 331 ],
		"L_EyelidLower1": [ 260, 256 ],
		"L_EyelidLower": [ 255, 254 ],
		"L_EyelidLower2": [ 267, 255 ],
		"L_LipUpper": [ 244, 322 ],
		"LipUpper": [ 232, 318 ],
		"L_LipCorner": [ 269, 324 ],
		"R_LipUpperOuter": [ 232, 309 ],
		"R_LipUpper": [ 230, 313 ],
		"L_LipUpperOuter": [ 254, 323 ],
		"R_LipCorner": [ 240, 308 ],
		"L_EyeCornerOuter": [ 274, 250 ],
		"L_EyeCornerOuter2": [ 274, 253 ],
		"L_EyeCornerOuter1": [ 270, 250 ],
		"L_EyelashesCorner": [ 270, 250 ],
		"Nose": [ 231, 264 ],
		"R_Nostril": [ 228, 288 ],
		"NoseTip": [ 224, 286 ],
		"NoseLower": [ 230, 296 ],
		"L_Nostril": [ 248, 297 ],
		"C_NoseBridge": [ 225, 232 ],
		"R_Ear": [ 280, 237 ],
		"R_Ear1": [ 280, 237 ],
		"R_Ear3": [ 278, 232 ],
		"R_Ear2": [ 272, 214 ],
		"R_Ear4": [ 272, 255 ],
		"L_EyeCornerInner": [ 251, 249 ],
		"L_EyeCornerInner1": [ 251, 246 ],
		"L_EyeCornerInner2": [ 254, 250 ],
		"R_Eye": [ 234, 234 ],
		"R_Pupil": [ 224, 240 ],
		"R_EyeCornerOuter": [ 230, 239 ],
		"R_EyeCornerOuter1": [ 226, 238 ],
		"R_EyelashesCorner": [ 226, 238 ],
		"R_EyeCornerOuter2": [ 231, 240 ],
		"L_Eye": [ 268, 241 ],
		"L_Pupil": [ 257, 249 ],
		"R_EyeCornerInner": [ 230, 244 ],
		"R_EyeCornerInner2": [ 229, 246 ],
		"R_EyeCornerInner1": [ 228, 242 ],
		"L_Ear1": [ 368, 251 ],
		"L_Ear3": [ 393, 250 ],
		"L_Ear2": [ 390, 222 ],
		"L_Ear4": [ 365, 278 ],
		"L_EyelidUpper1": [ 253, 245 ],
		"L_EyelidUpper2": [ 262, 247 ],
		"L_EyelidUpper": [ 250, 244 ],
		"R_EyelidLower1": [ 225, 247 ],
		"R_EyelidLower2": [ 225, 244 ],
		"R_EyelidLower": [ 227, 247 ],
		"R_EyelidUpper": [ 223, 239 ],
		"R_EyelidUpper1": [ 219, 237 ],
		"R_EyelidUpper2": [ 219, 236 ],
		"C_NoseUpper": [ 228, 249 ]
	}
}