{
	"Overall":
	{
		"ImageEyesGazeDirection": [ 0.85862161190228936, 0.51260991755360552 ],
		"ImageHeadDirection": [ 0.92058178187525663, 0.3905498468561695 ]
	},
	"Landmarks":
	{
		"Neck": [ 320, 309 ],
		"L_Upperarm": [ 427, 401 ],
		"R_Upperarm": [ 213, 401 ],
		"R_LipLower": [ 350, 306 ],
		"L_LipLowerOuter": [ 373, 300 ],
		"R_LipLowerOuter": [ 342, 305 ],
		"L_LipLower": [ 368, 304 ],
		"LipLower": [ 360, 307 ],
		"L_EyelidLower1": [ 386, 236 ],
		"L_EyelidLower": [ 380, 235 ],
		"L_EyelidLower2": [ 390, 234 ],
		"L_LipUpper": [ 372, 291 ],
		"LipUpper": [ 363, 292 ],
		"L_LipCorner": [ 377, 294 ],
		"R_LipUpperOuter": [ 342, 294 ],
		"R_LipUpper": [ 350, 293 ],
		"L_LipUpperOuter": [ 375, 291 ],
		"R_LipCorner": [ 333, 298 ],
		"L_EyeCornerOuter": [ 389, 230 ],
		"L_EyeCornerOuter2": [ 388, 231 ],
		"L_EyeCornerOuter1": [ 391, 229 ],
		"L_EyelashesCorner": [ 391, 229 ],
		"Nose": [ 364, 247 ],
		"R_Nostril": [ 347, 276 ],
		"NoseTip": [ 369, 267 ],
		"NoseLower": [ 366, 277 ],
		"L_Nostril": [ 375, 274 ],
		"C_NoseBridge": [ 366, 215 ],
		"R_Ear": [ 266, 242 ],
		"R_Ear1": [ 266, 242 ],
		"R_Ear3": [ 248, 240 ],
		"R_Ear2": [ 246, 220 ],
		"R_Ear4": [ 264, 261 ],
		"L_EyeCornerInner": [ 373, 231 ],
		"L_EyeCornerInner1": [ 375, 228 ],
		"L_EyeCornerInner2": [ 375, 233 ],
		"R_Eye": [ 323, 225 ],
		"R_Pupil": [ 328, 230 ],
		"R_EyeCornerOuter": [ 310, 231 ],
		"R_EyeCornerOuter1": [ 313, 229 ],
		"R_EyelashesCorner": [ 313, 229 ],
		"R_EyeCornerOuter2": [ 311, 232 ],
		"L_Eye": [ 379, 225 ],
		"L_Pupil": [ 387, 229 ],
		"R_EyeCornerInner": [ 340, 232 ],
		"R_EyeCornerInner2": [ 338, 234 ],
		"R_EyeCornerInner1": [ 339, 229 ],
		"L_Ear1": [ 370, 239 ],
		"L_Ear3": [ 377, 238 ],
		"L_Ear2": [ 381, 220 ],
		"L_Ear4": [ 378, 256 ],
		"L_EyelidUpper1": [ 389, 223 ],
		"L_EyelidUpper2": [ 394, 224 ],
		"L_EyelidUpper": [ 381, 224 ],
		"R_EyelidLower1": [ 326, 237 ],
		"R_EyelidLower2": [ 316, 236 ],
		"R_EyelidLower": [ 333, 236 ],
		"R_EyelidUpper": [ 337, 225 ],
		"R_EyelidUpper1": [ 328, 224 ],
		"R_EyelidUpper2": [ 318, 226 ],
		"C_NoseUpper": [ 365, 232 ]
	}
}