{
	"Overall":
	{
		"ImageEyesGazeDirection": [ 0.80739112225789789, -0.59001658934231005 ],
		"ImageHeadDirection": [ 0.98521175481967449, -0.17134117475124774 ]
	},
	"Landmarks":
	{
		"Neck": [ 320, 309 ],
		"L_Upperarm": [ 427, 401 ],
		"R_Upperarm": [ 213, 401 ],
		"R_LipLower": [ 379, 278 ],
		"L_LipLowerOuter": [ 391, 276 ],
		"R_LipLowerOuter": [ 371, 277 ],
		"L_LipLower": [ 391, 277 ],
		"LipLower": [ 388, 278 ],
		"L_EyelidLower1": [ 395, 211 ],
		"L_EyelidLower": [ 391, 210 ],
		"L_EyelidLower2": [ 396, 212 ],
		"L_LipUpper": [ 392, 264 ],
		"LipUpper": [ 387, 263 ],
		"L_LipCorner": [ 391, 272 ],
		"R_LipUpperOuter": [ 370, 266 ],
		"R_LipUpper": [ 378, 264 ],
		"L_LipUpperOuter": [ 392, 267 ],
		"R_LipCorner": [ 362, 273 ],
		"L_EyeCornerOuter": [ 391, 209 ],
		"L_EyeCornerOuter2": [ 391, 210 ],
		"L_EyeCornerOuter1": [ 392, 208 ],
		"L_EyelashesCorner": [ 392, 208 ],
		"Nose": [ 386, 220 ],
		"R_Nostril": [ 374, 248 ],
		"NoseTip": [ 396, 237 ],
		"NoseLower": [ 391, 249 ],
		"L_Nostril": [ 394, 249 ],
		"C_NoseBridge": [ 381, 190 ],
		"R_Ear": [ 276, 241 ],
		"R_Ear1": [ 276, 241 ],
		"R_Ear3": [ 255, 240 ],
		"R_Ear2": [ 254, 217 ],
		"R_Ear4": [ 280, 259 ],
		"L_EyeCornerInner": [ 384, 207 ],
		"L_EyeCornerInner1": [ 385, 205 ],
		"L_EyeCornerInner2": [ 387, 209 ],
		"R_Eye": [ 346, 202 ],
		"R_Pupil": [ 353, 196 ],
		"R_EyeCornerOuter": [ 338, 200 ],
		"R_EyeCornerOuter1": [ 340, 198 ],
		"R_EyelashesCorner": [ 340, 198 ],
		"R_EyeCornerOuter2": [ 339, 201 ],
		"L_Eye": [ 384, 209 ],
		"L_Pupil": [ 392, 204 ],
		"R_EyeCornerInner": [ 362, 203 ],
		"R_EyeCornerInner2": [ 361, 204 ],
		"R_EyeCornerInner1": [ 361, 200 ],
		"L_Ear1": [ 355, 245 ],
		"L_Ear3": [ 357, 246 ],
		"L_Ear2": [ 359, 227 ],
		"L_Ear4": [ 366, 260 ],
		"L_EyelidUpper1": [ 392, 198 ],
		"L_EyelidUpper2": [ 394, 202 ],
		"L_EyelidUpper": [ 388, 199 ],
		"R_EyelidLower1": [ 354, 204 ],
		"R_EyelidLower2": [ 346, 203 ],
		"R_EyelidLower": [ 359, 205 ],
		"R_EyelidUpper": [ 359, 192 ],
		"R_EyelidUpper1": [ 353, 189 ],
		"R_EyelidUpper2": [ 345, 191 ],
		"C_NoseUpper": [ 384, 205 ]
	}
}