{
	"Overall":
	{
		"ImageEyesGazeDirection": [ -0.60459650288014222, 0.79653190061986989 ],
		"ImageHeadDirection": [ -0.81153434145149439, 0.58430472584507598 ]
	},
	"Landmarks":
	{
		"Neck": [ 320, 316 ],
		"L_Upperarm": [ 463, 418 ],
		"R_Upperarm": [ 177, 418 ],
		"R_LipLower": [ 275, 324 ],
		"L_LipLowerOuter": [ 311, 322 ],
		"R_LipLowerOuter": [ 269, 320 ],
		"L_LipLower": [ 300, 325 ],
		"LipLower": [ 287, 327 ],
		"L_EyelidLower1": [ 329, 241 ],
		"L_EyelidLower": [ 320, 241 ],
		"L_EyelidLower2": [ 338, 240 ],
		"L_LipUpper": [ 301, 311 ],
		"LipUpper": [ 285, 309 ],
		"L_LipCorner": [ 322, 314 ],
		"R_LipUpperOuter": [ 267, 307 ],
		"R_LipUpper": [ 273, 308 ],
		"L_LipUpperOuter": [ 312, 311 ],
		"R_LipCorner": [ 264, 310 ],
		"L_EyeCornerOuter": [ 343, 236 ],
		"L_EyeCornerOuter2": [ 342, 239 ],
		"L_EyeCornerOuter1": [ 342, 235 ],
		"L_EyelashesCorner": [ 342, 235 ],
		"Nose": [ 286, 250 ],
		"R_Nostril": [ 267, 282 ],
		"NoseTip": [ 282, 274 ],
		"NoseLower": [ 285, 286 ],
		"L_Nostril": [ 311, 284 ],
		"C_NoseBridge": [ 286, 219 ],
		"R_Ear": [ 263, 243 ],
		"R_Ear1": [ 263, 243 ],
		"R_Ear3": [ 249, 242 ],
		"R_Ear2": [ 244, 222 ],
		"R_Ear4": [ 253, 262 ],
		"L_EyeCornerInner": [ 313, 237 ],
		"L_EyeCornerInner1": [ 315, 234 ],
		"L_EyeCornerInner2": [ 316, 238 ],
		"R_Eye": [ 264, 225 ],
		"R_Pupil": [ 256, 234 ],
		"R_EyeCornerOuter": [ 254, 235 ],
		"R_EyeCornerOuter1": [ 250, 233 ],
		"R_EyelashesCorner": [ 250, 233 ],
		"R_EyeCornerOuter2": [ 254, 236 ],
		"L_Eye": [ 330, 226 ],
		"L_Pupil": [ 325, 236 ],
		"R_EyeCornerInner": [ 271, 236 ],
		"R_EyeCornerInner2": [ 269, 238 ],
		"R_EyeCornerInner1": [ 268, 233 ],
		"L_Ear1": [ 383, 244 ],
		"L_Ear3": [ 402, 244 ],
		"L_Ear2": [ 404, 222 ],
		"L_Ear4": [ 386, 267 ],
		"L_EyelidUpper1": [ 328, 231 ],
		"L_EyelidUpper2": [ 339, 232 ],
		"L_EyelidUpper": [ 317, 231 ],
		"R_EyelidLower1": [ 258, 240 ],
		"R_EyelidLower2": [ 252, 239 ],
		"R_EyelidLower": [ 265, 239 ],
		"R_EyelidUpper": [ 264, 232 ],
		"R_EyelidUpper1": [ 254, 232 ],
		"R_EyelidUpper2": [ 247, 232 ],
		"C_NoseUpper": [ 286, 234 ]
	}
}