{
	"Overall":
	{
		"ImageEyesGazeDirection": [ 0.90152305746827355, 0.43273106758477131 ],
		"ImageHeadDirection": [ 0.95528589069134573, -0.2956837280711308 ]
	},
	"Landmarks":
	{
		"Neck": [ 320, 316 ],
		"L_Upperarm": [ 463, 418 ],
		"R_Upperarm": [ 177, 418 ],
		"R_LipLower": [ 372, 283 ],
		"L_LipLowerOuter": [ 395, 282 ],
		"R_LipLowerOuter": [ 362, 282 ],
		"L_LipLower": [ 391, 282 ],
		"LipLower": [ 385, 285 ],
		"L_EyelidLower1": [ 393, 210 ],
		"L_EyelidLower": [ 387, 208 ],
		"L_EyelidLower2": [ 396, 210 ],
		"L_LipUpper": [ 394, 268 ],
		"LipUpper": [ 385, 266 ],
		"L_LipCorner": [ 395, 277 ],
		"R_LipUpperOuter": [ 360, 269 ],
		"R_LipUpper": [ 371, 267 ],
		"L_LipUpperOuter": [ 396, 271 ],
		"R_LipCorner": [ 348, 277 ],
		"L_EyeCornerOuter": [ 392, 210 ],
		"L_EyeCornerOuter2": [ 392, 213 ],
		"L_EyeCornerOuter1": [ 396, 207 ],
		"L_EyelashesCorner": [ 396, 207 ],
		"Nose": [ 378, 210 ],
		"R_Nostril": [ 363, 245 ],
		"NoseTip": [ 389, 232 ],
		"NoseLower": [ 384, 245 ],
		"L_Nostril": [ 391, 247 ],
		"C_NoseBridge": [ 373, 181 ],
		"R_Ear": [ 260, 238 ],
		"R_Ear1": [ 260, 238 ],
		"R_Ear3": [ 239, 240 ],
		"R_Ear2": [ 239, 216 ],
		"R_Ear4": [ 258, 253 ],
		"L_EyeCornerInner": [ 383, 203 ],
		"L_EyeCornerInner1": [ 385, 200 ],
		"L_EyeCornerInner2": [ 385, 205 ],
		"R_Eye": [ 331, 194 ],
		"R_Pupil": [ 338, 198 ],
		"R_EyeCornerOuter": [ 321, 202 ],
		"R_EyeCornerOuter1": [ 323, 198 ],
		"R_EyelashesCorner": [ 323, 198 ],
		"R_EyeCornerOuter2": [ 320, 203 ],
		"L_Eye": [ 384, 200 ],
		"L_Pupil": [ 393, 204 ],
		"R_EyeCornerInner": [ 350, 200 ],
		"R_EyeCornerInner2": [ 347, 201 ],
		"R_EyeCornerInner1": [ 348, 196 ],
		"L_Ear1": [ 361, 244 ],
		"L_Ear3": [ 367, 246 ],
		"L_Ear2": [ 367, 228 ],
		"L_Ear4": [ 373, 257 ],
		"L_EyelidUpper1": [ 397, 197 ],
		"L_EyelidUpper2": [ 400, 200 ],
		"L_EyelidUpper": [ 390, 197 ],
		"R_EyelidLower1": [ 336, 204 ],
		"R_EyelidLower2": [ 327, 202 ],
		"R_EyelidLower": [ 344, 204 ],
		"R_EyelidUpper": [ 347, 190 ],
		"R_EyelidUpper1": [ 339, 189 ],
		"R_EyelidUpper2": [ 327, 191 ],
		"C_NoseUpper": [ 377, 195 ]
	}
}