{
	"Overall":
	{
		"ImageEyesGazeDirection": [ 0.65994099063671186, 0.75131743549410279 ],
		"ImageHeadDirection": [ 0.1414213562373095, 0.98994949366116647 ]
	},
	"Landmarks":
	{
		"Neck": [ 320, 309 ],
		"L_Upperarm": [ 427, 401 ],
		"R_Upperarm": [ 213, 401 ],
		"R_LipLower": [ 317, 336 ],
		"L_LipLowerOuter": [ 342, 331 ],
		"R_LipLowerOuter": [ 310, 333 ],
		"L_LipLower": [ 336, 335 ],
		"LipLower": [ 327, 338 ],
		"L_EyelidLower1": [ 366, 271 ],
		"L_EyelidLower": [ 358, 270 ],
		"L_EyelidLower2": [ 373, 268 ],
		"L_LipUpper": [ 339, 325 ],
		"LipUpper": [ 328, 327 ],
		"L_LipCorner": [ 349, 325 ],
		"R_LipUpperOuter": [ 308, 325 ],
		"R_LipUpper": [ 316, 326 ],
		"L_LipUpperOuter": [ 345, 324 ],
		"R_LipCorner": [ 302, 327 ],
		"L_EyeCornerOuter": [ 374, 259 ],
		"L_EyeCornerOuter2": [ 374, 261 ],
		"L_EyeCornerOuter1": [ 375, 259 ],
		"L_EyelashesCorner": [ 375, 259 ],
		"Nose": [ 329, 288 ],
		"R_Nostril": [ 311, 312 ],
		"NoseTip": [ 328, 311 ],
		"NoseLower": [ 328, 317 ],
		"L_Nostril": [ 343, 311 ],
		"C_NoseBridge": [ 330, 262 ],
		"R_Ear": [ 264, 243 ],
		"R_Ear1": [ 264, 243 ],
		"R_Ear3": [ 250, 238 ],
		"R_Ear2": [ 245, 220 ],
		"R_Ear4": [ 259, 264 ],
		"L_EyeCornerInner": [ 349, 266 ],
		"L_EyeCornerInner1": [ 351, 265 ],
		"L_EyeCornerInner2": [ 351, 269 ],
		"R_Eye": [ 293, 257 ],
		"R_Pupil": [ 297, 266 ],
		"R_EyeCornerOuter": [ 279, 260 ],
		"R_EyeCornerOuter1": [ 279, 261 ],
		"R_EyelashesCorner": [ 279, 261 ],
		"R_EyeCornerOuter2": [ 279, 262 ],
		"L_Eye": [ 361, 256 ],
		"L_Pupil": [ 369, 263 ],
		"R_EyeCornerInner": [ 308, 267 ],
		"R_EyeCornerInner2": [ 305, 268 ],
		"R_EyeCornerInner1": [ 305, 264 ],
		"L_Ear1": [ 376, 241 ],
		"L_Ear3": [ 388, 237 ],
		"L_Ear2": [ 393, 219 ],
		"L_Ear4": [ 382, 261 ],
		"L_EyelidUpper1": [ 367, 261 ],
		"L_EyelidUpper2": [ 376, 260 ],
		"L_EyelidUpper": [ 357, 262 ],
		"R_EyelidLower1": [ 290, 272 ],
		"R_EyelidLower2": [ 282, 269 ],
		"R_EyelidLower": [ 299, 272 ],
		"R_EyelidUpper": [ 301, 263 ],
		"R_EyelidUpper1": [ 291, 263 ],
		"R_EyelidUpper2": [ 281, 263 ],
		"C_NoseUpper": [ 329, 276 ]
	}
}