{
	"Overall":
	{
		"ImageEyesGazeDirection": [ -0.99852642046615281, -0.054267740242725696 ],
		"ImageHeadDirection": [ -0.95292578001326189, -0.30320365727694698 ]
	},
	"Landmarks":
	{
		"Neck": [ 320, 309 ],
		"L_Upperarm": [ 427, 401 ],
		"R_Upperarm": [ 213, 401 ],
		"R_LipLower": [ 249, 266 ],
		"L_LipLowerOuter": [ 268, 264 ],
		"R_LipLowerOuter": [ 247, 266 ],
		"L_LipLower": [ 261, 265 ],
		"LipLower": [ 253, 267 ],
		"L_EyelidLower1": [ 293, 202 ],
		"L_EyelidLower": [ 287, 203 ],
		"L_EyelidLower2": [ 300, 201 ],
		"L_LipUpper": [ 263, 252 ],
		"LipUpper": [ 253, 251 ],
		"L_LipCorner": [ 277, 259 ],
		"R_LipUpperOuter": [ 247, 255 ],
		"R_LipUpper": [ 248, 253 ],
		"L_LipUpperOuter": [ 271, 254 ],
		"R_LipCorner": [ 246, 262 ],
		"L_EyeCornerOuter": [ 307, 199 ],
		"L_EyeCornerOuter2": [ 307, 201 ],
		"L_EyeCornerOuter1": [ 305, 197 ],
		"L_EyelashesCorner": [ 305, 197 ],
		"Nose": [ 260, 211 ],
		"R_Nostril": [ 249, 239 ],
		"NoseTip": [ 249, 224 ],
		"NoseLower": [ 252, 235 ],
		"L_Nostril": [ 268, 236 ],
		"C_NoseBridge": [ 264, 185 ],
		"R_Ear": [ 284, 245 ],
		"R_Ear1": [ 284, 245 ],
		"R_Ear3": [ 280, 247 ],
		"R_Ear2": [ 279, 231 ],
		"R_Ear4": [ 272, 257 ],
		"L_EyeCornerInner": [ 284, 202 ],
		"L_EyeCornerInner1": [ 285, 198 ],
		"L_EyeCornerInner2": [ 286, 203 ],
		"R_Eye": [ 261, 207 ],
		"R_Pupil": [ 251, 207 ],
		"R_EyeCornerOuter": [ 254, 213 ],
		"R_EyeCornerOuter1": [ 252, 210 ],
		"R_EyelashesCorner": [ 252, 210 ],
		"R_EyeCornerOuter2": [ 255, 214 ],
		"L_Eye": [ 300, 197 ],
		"L_Pupil": [ 291, 196 ],
		"R_EyeCornerInner": [ 261, 207 ],
		"R_EyeCornerInner2": [ 259, 208 ],
		"R_EyeCornerInner1": [ 259, 204 ],
		"L_Ear1": [ 369, 235 ],
		"L_Ear3": [ 388, 236 ],
		"L_Ear2": [ 389, 214 ],
		"L_Ear4": [ 365, 250 ],
		"L_EyelidUpper1": [ 292, 189 ],
		"L_EyelidUpper2": [ 300, 190 ],
		"L_EyelidUpper": [ 286, 192 ],
		"R_EyelidLower1": [ 251, 212 ],
		"R_EyelidLower2": [ 249, 214 ],
		"R_EyelidLower": [ 255, 210 ],
		"R_EyelidUpper": [ 255, 200 ],
		"R_EyelidUpper1": [ 250, 201 ],
		"R_EyelidUpper2": [ 248, 204 ],
		"C_NoseUpper": [ 261, 198 ]
	}
}