{
	"Overall":
	{
		"ImageEyesGazeDirection": [ 0.95782628522115132, 0.28734788556634538 ],
		"ImageHeadDirection": [ 0.95619995550743164, -0.29271427209411172 ]
	},
	"Landmarks":
	{
		"Neck": [ 320, 315 ],
		"L_Upperarm": [ 456, 418 ],
		"R_Upperarm": [ 184, 418 ],
		"R_LipLower": [ 394, 275 ],
		"L_LipLowerOuter": [ 406, 277 ],
		"R_LipLowerOuter": [ 383, 275 ],
		"L_LipLower": [ 407, 276 ],
		"LipLower": [ 403, 278 ],
		"L_EyelidLower1": [ 395, 212 ],
		"L_EyelidLower": [ 391, 209 ],
		"L_EyelidLower2": [ 397, 213 ],
		"L_LipUpper": [ 409, 262 ],
		"LipUpper": [ 404, 259 ],
		"L_LipCorner": [ 402, 272 ],
		"R_LipUpperOuter": [ 382, 262 ],
		"R_LipUpper": [ 393, 260 ],
		"L_LipUpperOuter": [ 409, 265 ],
		"R_LipCorner": [ 367, 271 ],
		"L_EyeCornerOuter": [ 393, 213 ],
		"L_EyeCornerOuter2": [ 393, 214 ],
		"L_EyeCornerOuter1": [ 396, 210 ],
		"L_EyelashesCorner": [ 396, 210 ],
		"Nose": [ 389, 210 ],
		"R_Nostril": [ 379, 237 ],
		"NoseTip": [ 401, 224 ],
		"NoseLower": [ 399, 238 ],
		"L_Nostril": [ 403, 241 ],
		"C_NoseBridge": [ 384, 181 ],
		"R_Ear": [ 263, 238 ],
		"R_Ear1": [ 263, 238 ],
		"R_Ear3": [ 239, 236 ],
		"R_Ear2": [ 239, 211 ],
		"R_Ear4": [ 268, 255 ],
		"L_EyeCornerInner": [ 388, 206 ],
		"L_EyeCornerInner1": [ 390, 203 ],
		"L_EyeCornerInner2": [ 389, 207 ],
		"R_Eye": [ 346, 193 ],
		"R_Pupil": [ 354, 196 ],
		"R_EyeCornerOuter": [ 339, 199 ],
		"R_EyeCornerOuter1": [ 342, 195 ],
		"R_EyelashesCorner": [ 342, 195 ],
		"R_EyeCornerOuter2": [ 339, 200 ],
		"L_Eye": [ 385, 204 ],
		"L_Pupil": [ 395, 207 ],
		"R_EyeCornerInner": [ 364, 199 ],
		"R_EyeCornerInner2": [ 362, 201 ],
		"R_EyeCornerInner1": [ 363, 196 ],
		"L_Ear1": [ 357, 248 ],
		"L_Ear3": [ 359, 251 ],
		"L_Ear2": [ 359, 232 ],
		"L_Ear4": [ 369, 263 ],
		"L_EyelidUpper1": [ 398, 201 ],
		"L_EyelidUpper2": [ 400, 205 ],
		"L_EyelidUpper": [ 393, 201 ],
		"R_EyelidLower1": [ 354, 201 ],
		"R_EyelidLower2": [ 346, 200 ],
		"R_EyelidLower": [ 360, 201 ],
		"R_EyelidUpper": [ 363, 191 ],
		"R_EyelidUpper1": [ 357, 189 ],
		"R_EyelidUpper2": [ 348, 190 ],
		"C_NoseUpper": [ 387, 196 ]
	}
}