{
	"Overall":
	{
		"ImageEyesGazeDirection": [ 0.73480344462748792, 0.67828010273306583 ],
		"ImageHeadDirection": [ -0.87415727612153771, -0.48564293117863205 ]
	},
	"Landmarks":
	{
		"Neck": [ 320, 309 ],
		"L_Upperarm": [ 427, 401 ],
		"R_Upperarm": [ 213, 401 ],
		"R_LipLower": [ 287, 277 ],
		"L_LipLowerOuter": [ 314, 275 ],
		"R_LipLowerOuter": [ 282, 276 ],
		"L_LipLower": [ 306, 276 ],
		"LipLower": [ 296, 279 ],
		"L_EyelidLower1": [ 335, 211 ],
		"L_EyelidLower": [ 327, 210 ],
		"L_EyelidLower2": [ 343, 211 ],
		"L_LipUpper": [ 308, 263 ],
		"LipUpper": [ 296, 261 ],
		"L_LipCorner": [ 323, 271 ],
		"R_LipUpperOuter": [ 281, 265 ],
		"R_LipUpper": [ 286, 262 ],
		"L_LipUpperOuter": [ 316, 265 ],
		"R_LipCorner": [ 275, 271 ],
		"L_EyeCornerOuter": [ 346, 208 ],
		"L_EyeCornerOuter2": [ 346, 209 ],
		"L_EyeCornerOuter1": [ 346, 206 ],
		"L_EyelashesCorner": [ 346, 206 ],
		"Nose": [ 298, 216 ],
		"R_Nostril": [ 282, 246 ],
		"NoseTip": [ 293, 232 ],
		"NoseLower": [ 295, 245 ],
		"L_Nostril": [ 314, 245 ],
		"C_NoseBridge": [ 299, 187 ],
		"R_Ear": [ 271, 241 ],
		"R_Ear1": [ 271, 241 ],
		"R_Ear3": [ 263, 242 ],
		"R_Ear2": [ 261, 224 ],
		"R_Ear4": [ 263, 255 ],
		"L_EyeCornerInner": [ 319, 207 ],
		"L_EyeCornerInner1": [ 320, 203 ],
		"L_EyeCornerInner2": [ 321, 209 ],
		"R_Eye": [ 277, 207 ],
		"R_Pupil": [ 276, 208 ],
		"R_EyeCornerOuter": [ 265, 212 ],
		"R_EyeCornerOuter1": [ 263, 209 ],
		"R_EyelashesCorner": [ 263, 209 ],
		"R_EyeCornerOuter2": [ 265, 214 ],
		"L_Eye": [ 334, 203 ],
		"L_Pupil": [ 337, 205 ],
		"R_EyeCornerInner": [ 287, 209 ],
		"R_EyeCornerInner2": [ 285, 211 ],
		"R_EyeCornerInner1": [ 285, 206 ],
		"L_Ear1": [ 373, 239 ],
		"L_Ear3": [ 388, 240 ],
		"L_Ear2": [ 389, 221 ],
		"L_Ear4": [ 378, 253 ],
		"L_EyelidUpper1": [ 334, 198 ],
		"L_EyelidUpper2": [ 343, 200 ],
		"L_EyelidUpper": [ 325, 199 ],
		"R_EyelidLower1": [ 271, 214 ],
		"R_EyelidLower2": [ 265, 214 ],
		"R_EyelidLower": [ 279, 213 ],
		"R_EyelidUpper": [ 279, 202 ],
		"R_EyelidUpper1": [ 271, 202 ],
		"R_EyelidUpper2": [ 264, 205 ],
		"C_NoseUpper": [ 298, 202 ]
	}
}