{
	"Overall":
	{
		"ImageEyesGazeDirection": [ 0.61828425727828062, -0.78595456433679733 ],
		"ImageHeadDirection": [ 0.89442719099991586, -0.44721359549995793 ]
	},
	"Landmarks":
	{
		"Neck": [ 320, 315 ],
		"L_Upperarm": [ 456, 418 ],
		"R_Upperarm": [ 184, 418 ],
		"R_LipLower": [ 392, 260 ],
		"L_LipLowerOuter": [ 404, 264 ],
		"R_LipLowerOuter": [ 383, 259 ],
		"L_LipLower": [ 404, 262 ],
		"LipLower": [ 401, 260 ],
		"L_EyelidLower1": [ 392, 202 ],
		"L_EyelidLower": [ 388, 200 ],
		"L_EyelidLower2": [ 393, 204 ],
		"L_LipUpper": [ 404, 249 ],
		"LipUpper": [ 400, 244 ],
		"L_LipCorner": [ 402, 262 ],
		"R_LipUpperOuter": [ 381, 246 ],
		"R_LipUpper": [ 390, 244 ],
		"L_LipUpperOuter": [ 404, 253 ],
		"R_LipCorner": [ 371, 255 ],
		"L_EyeCornerOuter": [ 387, 204 ],
		"L_EyeCornerOuter2": [ 388, 205 ],
		"L_EyeCornerOuter1": [ 388, 202 ],
		"L_EyelashesCorner": [ 388, 202 ],
		"Nose": [ 388, 201 ],
		"R_Nostril": [ 382, 226 ],
		"NoseTip": [ 404, 211 ],
		"NoseLower": [ 400, 226 ],
		"L_Nostril": [ 399, 232 ],
		"C_NoseBridge": [ 381, 177 ],
		"R_Ear": [ 266, 233 ],
		"R_Ear1": [ 266, 233 ],
		"R_Ear3": [ 244, 235 ],
		"R_Ear2": [ 242, 212 ],
		"R_Ear4": [ 271, 246 ],
		"L_EyeCornerInner": [ 381, 197 ],
		"L_EyeCornerInner1": [ 382, 195 ],
		"L_EyeCornerInner2": [ 384, 198 ],
		"R_Eye": [ 344, 188 ],
		"R_Pupil": [ 350, 179 ],
		"R_EyeCornerOuter": [ 336, 183 ],
		"R_EyeCornerOuter1": [ 337, 180 ],
		"R_EyelashesCorner": [ 337, 180 ],
		"R_EyeCornerOuter2": [ 337, 183 ],
		"L_Eye": [ 379, 204 ],
		"L_Pupil": [ 386, 196 ],
		"R_EyeCornerInner": [ 361, 187 ],
		"R_EyeCornerInner2": [ 360, 187 ],
		"R_EyeCornerInner1": [ 359, 184 ],
		"L_Ear1": [ 352, 252 ],
		"L_Ear3": [ 352, 258 ],
		"L_Ear2": [ 351, 241 ],
		"L_Ear4": [ 366, 264 ],
		"L_EyelidUpper1": [ 387, 192 ],
		"L_EyelidUpper2": [ 390, 197 ],
		"L_EyelidUpper": [ 384, 192 ],
		"R_EyelidLower1": [ 353, 184 ],
		"R_EyelidLower2": [ 345, 183 ],
		"R_EyelidLower": [ 358, 186 ],
		"R_EyelidUpper": [ 355, 177 ],
		"R_EyelidUpper1": [ 350, 173 ],
		"R_EyelidUpper2": [ 342, 173 ],
		"C_NoseUpper": [ 384, 187 ]
	}
}