{
	"Overall":
	{
		"ImageEyesGazeDirection": [ -0.99388373467361879, 0.11043152607484653 ],
		"ImageHeadDirection": [ 0.87789557291438436, -0.47885213068057331 ]
	},
	"Landmarks":
	{
		"Neck": [ 320, 309 ],
		"L_Upperarm": [ 427, 401 ],
		"R_Upperarm": [ 213, 401 ],
		"R_LipLower": [ 322, 285 ],
		"L_LipLowerOuter": [ 351, 282 ],
		"R_LipLowerOuter": [ 314, 284 ],
		"L_LipLower": [ 343, 284 ],
		"LipLower": [ 334, 287 ],
		"L_EyelidLower1": [ 363, 215 ],
		"L_EyelidLower": [ 355, 214 ],
		"L_EyelidLower2": [ 370, 214 ],
		"L_LipUpper": [ 346, 270 ],
		"LipUpper": [ 334, 269 ],
		"L_LipCorner": [ 357, 277 ],
		"R_LipUpperOuter": [ 313, 272 ],
		"R_LipUpper": [ 321, 270 ],
		"L_LipUpperOuter": [ 352, 272 ],
		"R_LipCorner": [ 305, 278 ],
		"L_EyeCornerOuter": [ 371, 212 ],
		"L_EyeCornerOuter2": [ 371, 213 ],
		"L_EyeCornerOuter1": [ 372, 209 ],
		"L_EyelashesCorner": [ 372, 209 ],
		"Nose": [ 332, 221 ],
		"R_Nostril": [ 314, 251 ],
		"NoseTip": [ 334, 238 ],
		"NoseLower": [ 333, 251 ],
		"L_Nostril": [ 350, 251 ],
		"C_NoseBridge": [ 332, 192 ],
		"R_Ear": [ 266, 239 ],
		"R_Ear1": [ 266, 239 ],
		"R_Ear3": [ 253, 240 ],
		"R_Ear2": [ 252, 221 ],
		"R_Ear4": [ 261, 254 ],
		"L_EyeCornerInner": [ 347, 211 ],
		"L_EyeCornerInner1": [ 349, 208 ],
		"L_EyeCornerInner2": [ 350, 212 ],
		"R_Eye": [ 298, 207 ],
		"R_Pupil": [ 292, 207 ],
		"R_EyeCornerOuter": [ 285, 211 ],
		"R_EyeCornerOuter1": [ 286, 208 ],
		"R_EyelashesCorner": [ 286, 208 ],
		"R_EyeCornerOuter2": [ 286, 212 ],
		"L_Eye": [ 358, 208 ],
		"L_Pupil": [ 357, 209 ],
		"R_EyeCornerInner": [ 311, 210 ],
		"R_EyeCornerInner2": [ 309, 211 ],
		"R_EyeCornerInner1": [ 310, 207 ],
		"L_Ear1": [ 371, 240 ],
		"L_Ear3": [ 381, 241 ],
		"L_Ear2": [ 382, 223 ],
		"L_Ear4": [ 378, 255 ],
		"L_EyelidUpper1": [ 363, 202 ],
		"L_EyelidUpper2": [ 371, 205 ],
		"L_EyelidUpper": [ 355, 203 ],
		"R_EyelidLower1": [ 295, 214 ],
		"R_EyelidLower2": [ 287, 213 ],
		"R_EyelidLower": [ 303, 213 ],
		"R_EyelidUpper": [ 305, 202 ],
		"R_EyelidUpper1": [ 296, 201 ],
		"R_EyelidUpper2": [ 287, 203 ],
		"C_NoseUpper": [ 332, 207 ]
	}
}