{
	"Overall":
	{
		"ImageEyesGazeDirection": [ 0.5935421451838977, 0.80480290872392912 ],
		"ImageHeadDirection": [ 0.39958542051392815, 0.91669596470842341 ]
	},
	"Landmarks":
	{
		"Neck": [ 320, 307 ],
		"L_Upperarm": [ 418, 400 ],
		"R_Upperarm": [ 222, 400 ],
		"R_LipLower": [ 330, 335 ],
		"L_LipLowerOuter": [ 354, 328 ],
		"R_LipLowerOuter": [ 322, 332 ],
		"L_LipLower": [ 349, 332 ],
		"LipLower": [ 340, 335 ],
		"L_EyelidLower1": [ 378, 269 ],
		"L_EyelidLower": [ 371, 268 ],
		"L_EyelidLower2": [ 385, 265 ],
		"L_LipUpper": [ 353, 323 ],
		"LipUpper": [ 342, 325 ],
		"L_LipCorner": [ 360, 321 ],
		"R_LipUpperOuter": [ 322, 324 ],
		"R_LipUpper": [ 330, 325 ],
		"L_LipUpperOuter": [ 357, 321 ],
		"R_LipCorner": [ 314, 326 ],
		"L_EyeCornerOuter": [ 384, 258 ],
		"L_EyeCornerOuter2": [ 384, 259 ],
		"L_EyeCornerOuter1": [ 385, 258 ],
		"L_EyelashesCorner": [ 385, 258 ],
		"Nose": [ 346, 286 ],
		"R_Nostril": [ 327, 310 ],
		"NoseTip": [ 347, 308 ],
		"NoseLower": [ 345, 313 ],
		"L_Nostril": [ 358, 308 ],
		"C_NoseBridge": [ 349, 257 ],
		"R_Ear": [ 263, 246 ],
		"R_Ear1": [ 263, 246 ],
		"R_Ear3": [ 250, 238 ],
		"R_Ear2": [ 248, 220 ],
		"R_Ear4": [ 260, 265 ],
		"L_EyeCornerInner": [ 363, 265 ],
		"L_EyeCornerInner1": [ 366, 263 ],
		"L_EyeCornerInner2": [ 365, 267 ],
		"R_Eye": [ 308, 257 ],
		"R_Pupil": [ 313, 267 ],
		"R_EyeCornerOuter": [ 294, 263 ],
		"R_EyeCornerOuter1": [ 295, 264 ],
		"R_EyelashesCorner": [ 295, 264 ],
		"R_EyeCornerOuter2": [ 295, 265 ],
		"L_Eye": [ 372, 254 ],
		"L_Pupil": [ 380, 262 ],
		"R_EyeCornerInner": [ 324, 267 ],
		"R_EyeCornerInner2": [ 321, 268 ],
		"R_EyeCornerInner1": [ 322, 265 ],
		"L_Ear1": [ 373, 241 ],
		"L_Ear3": [ 380, 233 ],
		"L_Ear2": [ 383, 215 ],
		"L_Ear4": [ 379, 258 ],
		"L_EyelidUpper1": [ 381, 261 ],
		"L_EyelidUpper2": [ 388, 259 ],
		"L_EyelidUpper": [ 372, 262 ],
		"R_EyelidLower1": [ 307, 273 ],
		"R_EyelidLower2": [ 298, 270 ],
		"R_EyelidLower": [ 316, 272 ],
		"R_EyelidUpper": [ 318, 264 ],
		"R_EyelidUpper1": [ 309, 265 ],
		"R_EyelidUpper2": [ 299, 265 ],
		"C_NoseUpper": [ 347, 272 ]
	}
}