{
	"Overall":
	{
		"ImageEyesGazeDirection": [ 0.49469838555499518, 0.86906473138039686 ],
		"ImageHeadDirection": [ 0.40905590409290915, 0.91250932451495126 ]
	},
	"Landmarks":
	{
		"Neck": [ 320, 316 ],
		"L_Upperarm": [ 463, 418 ],
		"R_Upperarm": [ 177, 418 ],
		"R_LipLower": [ 324, 340 ],
		"L_LipLowerOuter": [ 356, 334 ],
		"R_LipLowerOuter": [ 315, 336 ],
		"L_LipLower": [ 348, 338 ],
		"LipLower": [ 337, 342 ],
		"L_EyelidLower1": [ 376, 249 ],
		"L_EyelidLower": [ 368, 249 ],
		"L_EyelidLower2": [ 384, 247 ],
		"L_LipUpper": [ 353, 326 ],
		"LipUpper": [ 339, 328 ],
		"L_LipCorner": [ 363, 325 ],
		"R_LipUpperOuter": [ 314, 326 ],
		"R_LipUpper": [ 323, 327 ],
		"L_LipUpperOuter": [ 359, 325 ],
		"R_LipCorner": [ 305, 328 ],
		"L_EyeCornerOuter": [ 383, 243 ],
		"L_EyeCornerOuter2": [ 383, 244 ],
		"L_EyeCornerOuter1": [ 385, 242 ],
		"L_EyelashesCorner": [ 385, 242 ],
		"Nose": [ 338, 265 ],
		"R_Nostril": [ 313, 300 ],
		"NoseTip": [ 340, 293 ],
		"NoseLower": [ 338, 304 ],
		"L_Nostril": [ 360, 298 ],
		"C_NoseBridge": [ 339, 232 ],
		"R_Ear": [ 256, 240 ],
		"R_Ear1": [ 256, 240 ],
		"R_Ear3": [ 239, 236 ],
		"R_Ear2": [ 236, 215 ],
		"R_Ear4": [ 249, 262 ],
		"L_EyeCornerInner": [ 360, 246 ],
		"L_EyeCornerInner1": [ 362, 244 ],
		"L_EyeCornerInner2": [ 363, 247 ],
		"R_Eye": [ 297, 237 ],
		"R_Pupil": [ 298, 245 ],
		"R_EyeCornerOuter": [ 283, 244 ],
		"R_EyeCornerOuter1": [ 283, 243 ],
		"R_EyelashesCorner": [ 283, 243 ],
		"R_EyeCornerOuter2": [ 283, 246 ],
		"L_Eye": [ 370, 236 ],
		"L_Pupil": [ 377, 243 ],
		"R_EyeCornerInner": [ 314, 246 ],
		"R_EyeCornerInner2": [ 310, 248 ],
		"R_EyeCornerInner1": [ 311, 244 ],
		"L_Ear1": [ 380, 239 ],
		"L_Ear3": [ 393, 234 ],
		"L_Ear2": [ 398, 214 ],
		"L_Ear4": [ 388, 259 ],
		"L_EyelidUpper1": [ 378, 239 ],
		"L_EyelidUpper2": [ 386, 240 ],
		"L_EyelidUpper": [ 368, 240 ],
		"R_EyelidLower1": [ 294, 251 ],
		"R_EyelidLower2": [ 285, 249 ],
		"R_EyelidLower": [ 304, 251 ],
		"R_EyelidUpper": [ 305, 241 ],
		"R_EyelidUpper1": [ 295, 241 ],
		"R_EyelidUpper2": [ 284, 242 ],
		"C_NoseUpper": [ 339, 248 ]
	}
}