{
	"Overall":
	{
		"ImageEyesGazeDirection": [ 0.34276216020584394, 0.93942221686046123 ],
		"ImageHeadDirection": [ 0.91531503242276557, 0.40273861426601687 ]
	},
	"Landmarks":
	{
		"Neck": [ 320, 315 ],
		"L_Upperarm": [ 456, 418 ],
		"R_Upperarm": [ 184, 418 ],
		"R_LipLower": [ 340, 316 ],
		"L_LipLowerOuter": [ 369, 312 ],
		"R_LipLowerOuter": [ 331, 315 ],
		"L_LipLower": [ 362, 314 ],
		"LipLower": [ 353, 319 ],
		"L_EyelidLower1": [ 379, 233 ],
		"L_EyelidLower": [ 371, 231 ],
		"L_EyelidLower2": [ 385, 232 ],
		"L_LipUpper": [ 366, 300 ],
		"LipUpper": [ 354, 300 ],
		"L_LipCorner": [ 375, 305 ],
		"R_LipUpperOuter": [ 330, 302 ],
		"R_LipUpper": [ 340, 301 ],
		"L_LipUpperOuter": [ 371, 300 ],
		"R_LipCorner": [ 320, 308 ],
		"L_EyeCornerOuter": [ 385, 229 ],
		"L_EyeCornerOuter2": [ 384, 231 ],
		"L_EyeCornerOuter1": [ 388, 227 ],
		"L_EyelashesCorner": [ 388, 227 ],
		"Nose": [ 352, 243 ],
		"R_Nostril": [ 330, 278 ],
		"NoseTip": [ 356, 269 ],
		"NoseLower": [ 354, 280 ],
		"L_Nostril": [ 370, 276 ],
		"C_NoseBridge": [ 352, 205 ],
		"R_Ear": [ 257, 244 ],
		"R_Ear1": [ 257, 244 ],
		"R_Ear3": [ 239, 242 ],
		"R_Ear2": [ 237, 220 ],
		"R_Ear4": [ 252, 263 ],
		"L_EyeCornerInner": [ 365, 229 ],
		"L_EyeCornerInner1": [ 367, 226 ],
		"L_EyeCornerInner2": [ 367, 231 ],
		"R_Eye": [ 309, 219 ],
		"R_Pupil": [ 310, 228 ],
		"R_EyeCornerOuter": [ 296, 228 ],
		"R_EyeCornerOuter1": [ 297, 227 ],
		"R_EyelashesCorner": [ 297, 227 ],
		"R_EyeCornerOuter2": [ 297, 231 ],
		"L_Eye": [ 374, 220 ],
		"L_Pupil": [ 379, 228 ],
		"R_EyeCornerInner": [ 327, 228 ],
		"R_EyeCornerInner2": [ 323, 230 ],
		"R_EyeCornerInner1": [ 325, 226 ],
		"L_Ear1": [ 375, 243 ],
		"L_Ear3": [ 385, 241 ],
		"L_Ear2": [ 388, 222 ],
		"L_Ear4": [ 384, 260 ],
		"L_EyelidUpper1": [ 381, 224 ],
		"L_EyelidUpper2": [ 389, 225 ],
		"L_EyelidUpper": [ 372, 224 ],
		"R_EyelidLower1": [ 310, 233 ],
		"R_EyelidLower2": [ 300, 231 ],
		"R_EyelidLower": [ 319, 231 ],
		"R_EyelidUpper": [ 322, 224 ],
		"R_EyelidUpper1": [ 312, 224 ],
		"R_EyelidUpper2": [ 301, 225 ],
		"C_NoseUpper": [ 353, 224 ]
	}
}