{
	"Overall":
	{
		"ImageEyesGazeDirection": [ -0.75460552216350463, -0.65617871492478663 ],
		"ImageHeadDirection": [ -0.90968800386303394, -0.41529234958964595 ]
	},
	"Landmarks":
	{
		"Neck": [ 320, 315 ],
		"L_Upperarm": [ 456, 418 ],
		"R_Upperarm": [ 184, 418 ],
		"R_LipLower": [ 239, 267 ],
		"L_LipLowerOuter": [ 261, 264 ],
		"R_LipLowerOuter": [ 239, 268 ],
		"L_LipLower": [ 252, 265 ],
		"LipLower": [ 243, 265 ],
		"L_EyelidLower1": [ 292, 192 ],
		"L_EyelidLower": [ 286, 193 ],
		"L_EyelidLower2": [ 299, 191 ],
		"L_LipUpper": [ 254, 249 ],
		"LipUpper": [ 243, 248 ],
		"L_LipCorner": [ 272, 261 ],
		"R_LipUpperOuter": [ 238, 256 ],
		"R_LipUpper": [ 238, 252 ],
		"L_LipUpperOuter": [ 263, 252 ],
		"R_LipCorner": [ 241, 265 ],
		"L_EyeCornerOuter": [ 306, 191 ],
		"L_EyeCornerOuter2": [ 306, 193 ],
		"L_EyeCornerOuter1": [ 304, 188 ],
		"L_EyelashesCorner": [ 304, 188 ],
		"Nose": [ 253, 203 ],
		"R_Nostril": [ 242, 235 ],
		"NoseTip": [ 237, 215 ],
		"NoseLower": [ 242, 230 ],
		"L_Nostril": [ 262, 230 ],
		"C_NoseBridge": [ 259, 178 ],
		"R_Ear": [ 284, 251 ],
		"R_Ear1": [ 284, 251 ],
		"R_Ear3": [ 284, 255 ],
		"R_Ear2": [ 284, 238 ],
		"R_Ear4": [ 271, 263 ],
		"L_EyeCornerInner": [ 281, 191 ],
		"L_EyeCornerInner1": [ 281, 188 ],
		"L_EyeCornerInner2": [ 282, 192 ],
		"R_Eye": [ 260, 203 ],
		"R_Pupil": [ 256, 201 ],
		"R_EyeCornerOuter": [ 251, 209 ],
		"R_EyeCornerOuter1": [ 248, 206 ],
		"R_EyelashesCorner": [ 248, 206 ],
		"R_EyeCornerOuter2": [ 250, 210 ],
		"L_Eye": [ 298, 188 ],
		"L_Pupil": [ 298, 186 ],
		"R_EyeCornerInner": [ 259, 201 ],
		"R_EyeCornerInner2": [ 258, 203 ],
		"R_EyeCornerInner1": [ 258, 199 ],
		"L_Ear1": [ 375, 234 ],
		"L_Ear3": [ 396, 237 ],
		"L_Ear2": [ 400, 213 ],
		"L_Ear4": [ 370, 248 ],
		"L_EyelidUpper1": [ 290, 181 ],
		"L_EyelidUpper2": [ 299, 182 ],
		"L_EyelidUpper": [ 285, 185 ],
		"R_EyelidLower1": [ 249, 207 ],
		"R_EyelidLower2": [ 247, 208 ],
		"R_EyelidLower": [ 253, 205 ],
		"R_EyelidUpper": [ 253, 195 ],
		"R_EyelidUpper1": [ 248, 197 ],
		"R_EyelidUpper2": [ 246, 202 ],
		"C_NoseUpper": [ 256, 189 ]
	}
}