{
	"Overall":
	{
		"ImageEyesGazeDirection": [ 0.98893635286829751, -0.14834045293024462 ],
		"ImageHeadDirection": [ 0.70710678118654746, 0.70710678118654746 ]
	},
	"Landmarks":
	{
		"Neck": [ 320, 303 ],
		"L_Upperarm": [ 421, 390 ],
		"R_Upperarm": [ 219, 390 ],
		"R_LipLower": [ 342, 320 ],
		"L_LipLowerOuter": [ 367, 313 ],
		"R_LipLowerOuter": [ 333, 318 ],
		"L_LipLower": [ 361, 318 ],
		"LipLower": [ 353, 321 ],
		"L_EyelidLower1": [ 387, 244 ],
		"L_EyelidLower": [ 380, 244 ],
		"L_EyelidLower2": [ 393, 241 ],
		"L_LipUpper": [ 366, 306 ],
		"LipUpper": [ 356, 308 ],
		"L_LipCorner": [ 371, 306 ],
		"R_LipUpperOuter": [ 334, 308 ],
		"R_LipUpper": [ 343, 308 ],
		"L_LipUpperOuter": [ 370, 305 ],
		"R_LipCorner": [ 324, 310 ],
		"L_EyeCornerOuter": [ 391, 235 ],
		"L_EyeCornerOuter2": [ 392, 236 ],
		"L_EyeCornerOuter1": [ 392, 234 ],
		"L_EyelashesCorner": [ 392, 234 ],
		"Nose": [ 358, 263 ],
		"R_Nostril": [ 340, 291 ],
		"NoseTip": [ 362, 287 ],
		"NoseLower": [ 358, 294 ],
		"L_Nostril": [ 368, 289 ],
		"C_NoseBridge": [ 360, 231 ],
		"R_Ear": [ 267, 243 ],
		"R_Ear1": [ 267, 243 ],
		"R_Ear3": [ 250, 240 ],
		"R_Ear2": [ 247, 221 ],
		"R_Ear4": [ 263, 263 ],
		"L_EyeCornerInner": [ 371, 241 ],
		"L_EyeCornerInner1": [ 373, 238 ],
		"L_EyeCornerInner2": [ 374, 242 ],
		"R_Eye": [ 317, 238 ],
		"R_Pupil": [ 319, 239 ],
		"R_EyeCornerOuter": [ 304, 238 ],
		"R_EyeCornerOuter1": [ 305, 237 ],
		"R_EyelashesCorner": [ 305, 237 ],
		"R_EyeCornerOuter2": [ 304, 240 ],
		"L_Eye": [ 378, 236 ],
		"L_Pupil": [ 384, 236 ],
		"R_EyeCornerInner": [ 335, 243 ],
		"R_EyeCornerInner2": [ 332, 244 ],
		"R_EyeCornerInner1": [ 334, 241 ],
		"L_Ear1": [ 370, 238 ],
		"L_Ear3": [ 378, 234 ],
		"L_Ear2": [ 383, 219 ],
		"L_Ear4": [ 377, 256 ],
		"L_EyelidUpper1": [ 388, 232 ],
		"L_EyelidUpper2": [ 394, 232 ],
		"L_EyelidUpper": [ 380, 234 ],
		"R_EyelidLower1": [ 318, 247 ],
		"R_EyelidLower2": [ 309, 245 ],
		"R_EyelidLower": [ 327, 247 ],
		"R_EyelidUpper": [ 329, 234 ],
		"R_EyelidUpper1": [ 320, 233 ],
		"R_EyelidUpper2": [ 309, 234 ],
		"C_NoseUpper": [ 359, 248 ]
	}
}