{
	"Overall":
	{
		"ImageEyesGazeDirection": [ 0.71824022278917377, -0.69579521582701209 ],
		"ImageHeadDirection": [ 0.51897813424176409, 0.85478751522172902 ]
	},
	"Landmarks":
	{
		"Neck": [ 320, 303 ],
		"L_Upperarm": [ 421, 390 ],
		"R_Upperarm": [ 219, 390 ],
		"R_LipLower": [ 329, 321 ],
		"L_LipLowerOuter": [ 356, 316 ],
		"R_LipLowerOuter": [ 320, 319 ],
		"L_LipLower": [ 349, 320 ],
		"LipLower": [ 341, 323 ],
		"L_EyelidLower1": [ 377, 244 ],
		"L_EyelidLower": [ 369, 245 ],
		"L_EyelidLower2": [ 384, 242 ],
		"L_LipUpper": [ 354, 308 ],
		"LipUpper": [ 342, 310 ],
		"L_LipCorner": [ 361, 309 ],
		"R_LipUpperOuter": [ 321, 310 ],
		"R_LipUpper": [ 330, 310 ],
		"L_LipUpperOuter": [ 359, 308 ],
		"R_LipCorner": [ 312, 311 ],
		"L_EyeCornerOuter": [ 384, 235 ],
		"L_EyeCornerOuter2": [ 385, 237 ],
		"L_EyeCornerOuter1": [ 385, 234 ],
		"L_EyelashesCorner": [ 385, 234 ],
		"Nose": [ 344, 265 ],
		"R_Nostril": [ 326, 293 ],
		"NoseTip": [ 346, 290 ],
		"NoseLower": [ 344, 297 ],
		"L_Nostril": [ 357, 291 ],
		"C_NoseBridge": [ 345, 233 ],
		"R_Ear": [ 266, 242 ],
		"R_Ear1": [ 266, 242 ],
		"R_Ear3": [ 250, 239 ],
		"R_Ear2": [ 247, 220 ],
		"R_Ear4": [ 261, 262 ],
		"L_EyeCornerInner": [ 360, 242 ],
		"L_EyeCornerInner1": [ 362, 240 ],
		"L_EyeCornerInner2": [ 363, 243 ],
		"R_Eye": [ 305, 239 ],
		"R_Pupil": [ 306, 237 ],
		"R_EyeCornerOuter": [ 291, 237 ],
		"R_EyeCornerOuter1": [ 292, 236 ],
		"R_EyelashesCorner": [ 292, 236 ],
		"R_EyeCornerOuter2": [ 291, 239 ],
		"L_Eye": [ 370, 238 ],
		"L_Pupil": [ 375, 235 ],
		"R_EyeCornerInner": [ 322, 243 ],
		"R_EyeCornerInner2": [ 319, 244 ],
		"R_EyeCornerInner1": [ 320, 241 ],
		"L_Ear1": [ 372, 239 ],
		"L_Ear3": [ 382, 235 ],
		"L_Ear2": [ 387, 219 ],
		"L_Ear4": [ 379, 257 ],
		"L_EyelidUpper1": [ 378, 231 ],
		"L_EyelidUpper2": [ 386, 232 ],
		"L_EyelidUpper": [ 369, 234 ],
		"R_EyelidLower1": [ 305, 247 ],
		"R_EyelidLower2": [ 295, 245 ],
		"R_EyelidLower": [ 313, 247 ],
		"R_EyelidUpper": [ 315, 233 ],
		"R_EyelidUpper1": [ 306, 232 ],
		"R_EyelidUpper2": [ 295, 233 ],
		"C_NoseUpper": [ 345, 249 ]
	}
}